{"kind":"blogger#post","id":"62194067451547199","blog":{"id":"2360593805083673688"},"published":"2010-11-10T02:00:00-08:00","updated":"2010-11-10T02:00:07-08:00","url":"http://www.quietlikehorses.com/2010/11/wish-you-were-here-xoxo-tropical.html","selfLink":"https://www.googleapis.com/blogger/v3/blogs/2360593805083673688/posts/62194067451547199","title":"Wish You Were Here. xoxo, Tropical Paradise","content":"<div style=\"text-align: center;\"><a href=\"http://www.flickr.com/photos/thaimychu/1370948616/\" title=\"Phuket - August '07-30 by Thai Chu, on Flickr\"><img src=\"http://farm2.static.flickr.com/1154/1370948616_4a2c514536.jpg\" alt=\"Phuket - August '07-30\" height=\"375\" width=\"500\" /></a><br /></div><br /><div style=\"text-align: center;\"><a href=\"http://www.flickr.com/photos/thaimychu/1370057777/\" title=\"Phuket - August '07-36 by Thai Chu, on Flickr\"><img src=\"http://farm2.static.flickr.com/1269/1370057777_0e134b3848.jpg\" alt=\"Phuket - August '07-36\" height=\"375\" width=\"500\" /></a><br /></div>Work has been nuts lately since I've been working on this big project which seems to get bigger by the day. When things get really hectic, I can't help but think about my long overdue getaway to Hong Kong, Cambodia, and Thailand this coming January. (My last trip out of the country was back in 2008 when I went to <a href=\"http://bit.ly/djvtaU\">London for 3 days</a>!) I have my heart set on making it to the Phi Phi islands which are supposed to be amazing and exactly what I'll need after this work project wraps up. In the meantime, I've been ogling the pictures <a href=\"http://bit.ly/damyt0\">my friend Thai</a> took from his Thailand visit a few years back. Isn't the color of the water absolutely wild?","author":{"id":"06629562195146939698","displayName":"Sobrina Tung","url":"http://www.blogger.com/profile/06629562195146939698","image":{"url":"http://3.bp.blogspot.com/_mkw1MyhyGTY/TI8X4CO5nWI/AAAAAAAAERk/4p5D74gYdFE/S45/me.JPG"}},"replies":{"totalItems":"5","selfLink":"https://www.googleapis.com/blogger/v3/blogs/2360593805083673688/posts/62194067451547199/comments"},"labels":["To See"]}