{"kind":"blogger#post","id":"9208651559928975043","blog":{"id":"2360593805083673688"},"published":"2011-11-11T02:30:00-08:00","updated":"2011-11-11T02:30:01-08:00","url":"http://www.quietlikehorses.com/2011/11/scallop-feeling-edgy.html","selfLink":"https://www.googleapis.com/blogger/v3/blogs/2360593805083673688/posts/9208651559928975043","title":"Scallop: Feeling Edgy","content":"<div class=\"separator\" style=\"clear: both; text-align: center;\"><a href=\"http://2.bp.blogspot.com/-ti56Frd01iw/TrzIIluytCI/AAAAAAAAJt0/iD2nY6UrF5E/s1600/scalloped+borders.jpg\" imageanchor=\"1\" style=\"margin-left: 1em; margin-right: 1em;\"><img border=\"0\" src=\"http://2.bp.blogspot.com/-ti56Frd01iw/TrzIIluytCI/AAAAAAAAJt0/iD2nY6UrF5E/s1600/scalloped+borders.jpg\" /></a></div><div class=\"separator\" style=\"clear: both; text-align: center;\"><br />\n</div><div class=\"separator\" style=\"clear: both; text-align: left;\">Scalloped edges are on my current list of favorites. They can make almost anything look whimsical, don't you think? I got this black skirt to wear to holiday parties and because it makes me feel like I'm wearing a piece of a gingerbread house (of course, only in the good way). Here are a few other pretty pieces with this lovely subtle border.&nbsp;</div><div class=\"separator\" style=\"clear: both; text-align: left;\"><br />\n</div><div class=\"separator\" style=\"clear: both; text-align: left;\">1. <a href=\"http://bit.ly/uXgCs3\">Madewell silk scallop-wave dress</a></div><div class=\"separator\" style=\"clear: both; text-align: left;\">2. <a href=\"http://etsy.me/tqDNrO\">beaded headband</a></div><div class=\"separator\" style=\"clear: both; text-align: left;\">3. <a href=\"http://anthrpl.ge/t2ExF7\">Anthropologie scallop pencil skirt</a></div><div class=\"separator\" style=\"clear: both; text-align: left;\">4. <a href=\"http://etsy.me/rI9Bd8\">vintage stud earrings</a></div><div class=\"separator\" style=\"clear: both; text-align: left;\">5. <a href=\"http://bit.ly/rPmUiv\">Asos scallop edge bra</a></div>","author":{"id":"06629562195146939698","displayName":"Sobrina Tung","url":"http://www.blogger.com/profile/06629562195146939698","image":{"url":"http://3.bp.blogspot.com/_mkw1MyhyGTY/TI8X4CO5nWI/AAAAAAAAERk/4p5D74gYdFE/S45/me.JPG"}},"replies":{"totalItems":"1","selfLink":"https://www.googleapis.com/blogger/v3/blogs/2360593805083673688/posts/9208651559928975043/comments"},"labels":["To Wear"]}